Metadata-Version: 2.1
Name: gitfiler
Version: 0.1.1
Summary: Simple tool to download single file from GitHub or GitLab.
Home-page: https://github.com/samedamci/gitfiler
Author: samedamci
Author-email: samedamci@disroot.org
License: UNKNOWN
Project-URL: Source, https://github.com/samedamci/gitfiler
Project-URL: Tracker, https://github.com/samedamci/gitfiler/issues
Keywords: github gitlab downloader
Platform: UNKNOWN
Classifier: Development Status :: 5 - Production/Stable
Classifier: Intended Audience :: Developers
Classifier: License :: OSI Approved :: ISC License (ISCL)
Classifier: Programming Language :: Python
Classifier: Programming Language :: Python :: 3
Classifier: Programming Language :: Python :: 3.6
Classifier: Programming Language :: Python :: 3.7
Classifier: Programming Language :: Python :: 3.8
Classifier: Programming Language :: Python :: 3.9
Classifier: Programming Language :: Python :: Implementation :: CPython
Classifier: Programming Language :: Python :: Implementation :: PyPy
Classifier: Topic :: Software Development :: Libraries
Classifier: Typing :: Typed
Requires-Python: >=3.6,<4.0
License-File: LICENSE
